odoo8_addon_web_option_auto_color-8.0.0.1.0.99.dev9-py2.7-nspkg.pth
odoo8_addon_web_option_auto_color-8.0.0.1.0.99.dev9.dist-info/DESCRIPTION.rst
odoo8_addon_web_option_auto_color-8.0.0.1.0.99.dev9.dist-info/METADATA
odoo8_addon_web_option_auto_color-8.0.0.1.0.99.dev9.dist-info/RECORD
odoo8_addon_web_option_auto_color-8.0.0.1.0.99.dev9.dist-info/WHEEL
odoo8_addon_web_option_auto_color-8.0.0.1.0.99.dev9.dist-info/metadata.json
odoo8_addon_web_option_auto_color-8.0.0.1.0.99.dev9.dist-info/namespace_packages.txt
odoo8_addon_web_option_auto_color-8.0.0.1.0.99.dev9.dist-info/top_level.txt
odoo_addons/web_option_auto_color/README.rst
odoo_addons/web_option_auto_color/__init__.py
odoo_addons/web_option_auto_color/__openerp__.py
odoo_addons/web_option_auto_color/i18n/es.po
odoo_addons/web_option_auto_color/i18n/fi.po
odoo_addons/web_option_auto_color/i18n/fr.po
odoo_addons/web_option_auto_color/i18n/it.po
odoo_addons/web_option_auto_color/i18n/sl.po
odoo_addons/web_option_auto_color/i18n/tr.po
odoo_addons/web_option_auto_color/i18n/web_option_auto_color.pot
odoo_addons/web_option_auto_color/static/description/icon.png
odoo_addons/web_option_auto_color/static/src/js/view_list.js
odoo_addons/web_option_auto_color/static/src/xml/templates.xml
odoo_addons/web_option_auto_color/views/web_option_auto_color.xml
